sleep_scoring/__init__.py
sleep_scoring/_pyqt_module.py
sleep_scoring/config.py
sleep_scoring/data_url.json
sleep_scoring/gui/__init__.py
sleep_scoring/gui/sleep/__init__.py
sleep_scoring/gui/sleep/sleep.py
sleep_scoring/gui/sleep/interface/__init__.py
sleep_scoring/gui/sleep/interface/ui_init.py
sleep_scoring/gui/sleep/interface/gui/__init__.py
sleep_scoring/gui/sleep/interface/gui/sleep_gui.py
sleep_scoring/gui/sleep/interface/ui_elements/__init__.py
sleep_scoring/gui/sleep/interface/ui_elements/ui_annotate.py
sleep_scoring/gui/sleep/interface/ui_elements/ui_detection.py
sleep_scoring/gui/sleep/interface/ui_elements/ui_elements.py
sleep_scoring/gui/sleep/interface/ui_elements/ui_info.py
sleep_scoring/gui/sleep/interface/ui_elements/ui_menu.py
sleep_scoring/gui/sleep/interface/ui_elements/ui_panels.py
sleep_scoring/gui/sleep/interface/ui_elements/ui_scoring.py
sleep_scoring/gui/sleep/interface/ui_elements/ui_screenshot.py
sleep_scoring/gui/sleep/interface/ui_elements/ui_settings.py
sleep_scoring/gui/sleep/interface/ui_elements/ui_tools.py
sleep_scoring/gui/sleep/visuals/__init__.py
sleep_scoring/gui/sleep/visuals/marker.py
sleep_scoring/gui/sleep/visuals/visuals.py
sleep_scoring/io/__init__.py
sleep_scoring/io/dependencies.py
sleep_scoring/io/dialog.py
sleep_scoring/io/download.py
sleep_scoring/io/mneio.py
sleep_scoring/io/path.py
sleep_scoring/io/read_annotations.py
sleep_scoring/io/read_data.py
sleep_scoring/io/read_sleep.py
sleep_scoring/io/rw_config.py
sleep_scoring/io/rw_hypno.py
sleep_scoring/io/rw_nifti.py
sleep_scoring/io/rw_utils.py
sleep_scoring/io/write_data.py
sleep_scoring/io/write_image.py
sleep_scoring/io/write_table.py
sleep_scoring/io/write_template.py
sleep_scoring/mne/__init__.py
sleep_scoring/mne/plot_mne.py
sleep_scoring/objects/__init__.py
sleep_scoring/objects/cbar_obj.py
sleep_scoring/objects/hypno_obj.py
sleep_scoring/objects/image_obj.py
sleep_scoring/objects/pacmap_obj.py
sleep_scoring/objects/scene_obj.py
sleep_scoring/objects/tf_obj.py
sleep_scoring-0.0.4.dist-info/LICENSE
sleep_scoring-0.0.4.dist-info/METADATA
sleep_scoring-0.0.4.dist-info/WHEEL
sleep_scoring-0.0.4.dist-info/top_level.txt
sleep_scoring-0.0.4.dist-info/RECORD
